modulr_client/__init__.py
modulr_client/api/__init__.py
modulr_client/api/access_group/__init__.py
modulr_client/api/access_group/create_access_group.py
modulr_client/api/access_group/get_access_group.py
modulr_client/api/access_group/get_access_groups.py
modulr_client/api/access_group/update_access_group.py
modulr_client/api/accounts/__init__.py
modulr_client/api/accounts/block_account.py
modulr_client/api/accounts/close_account.py
modulr_client/api/accounts/create_account.py
modulr_client/api/accounts/edit_account.py
modulr_client/api/accounts/get_account.py
modulr_client/api/accounts/get_accounts.py
modulr_client/api/accounts/get_accounts_by_customer.py
modulr_client/api/accounts/unblock_account.py
modulr_client/api/accounts/update_secured_funding_limit.py
modulr_client/api/async_/__init__.py
modulr_client/api/async_/get_async_task.py
modulr_client/api/async_/get_async_tasks.py
modulr_client/api/async_/get_create_physical_card_async_tasks_by_account.py
modulr_client/api/beneficiaries/__init__.py
modulr_client/api/beneficiaries/create_beneficiary.py
modulr_client/api/beneficiaries/delete_beneficiaries.py
modulr_client/api/beneficiaries/get_beneficiaries.py
modulr_client/api/card_simulator/__init__.py
modulr_client/api/card_simulator/create_authorisation.py
modulr_client/api/card_simulator/reverse_authorisation.py
modulr_client/api/card_simulator/settle_authorisation.py
modulr_client/api/cards/__init__.py
modulr_client/api/cards/activate_card.py
modulr_client/api/cards/block_card.py
modulr_client/api/cards/cancel_card.py
modulr_client/api/cards/card_enquiry.py
modulr_client/api/cards/create_card.py
modulr_client/api/cards/create_physical_card.py
modulr_client/api/cards/generate_card_holder_token.py
modulr_client/api/cards/get_card.py
modulr_client/api/cards/get_card_activities.py
modulr_client/api/cards/get_cards.py
modulr_client/api/cards/get_cards_by_account.py
modulr_client/api/cards/get_secure_card_details.py
modulr_client/api/cards/replace_card.py
python_modulr_client-0.0.11.dist-info/LICENSE
python_modulr_client-0.0.11.dist-info/METADATA
python_modulr_client-0.0.11.dist-info/WHEEL
python_modulr_client-0.0.11.dist-info/RECORD
