Metadata-Version: 2.1
Name: python-modulr-client
Version: 0.0.11
Summary: Python client for Modulr APIs
Home-page: https://github.com/expobrain/python-modulr-client
License: MIT
Author: Daniele Esposti
Author-email: daniele.esposti@gmail.com
Requires-Python: >=3.7.2,<3.12
Classifier: License :: OSI Approved :: MIT License
Classifier: Programming Language :: Python :: 3
Classifier: Programming Language :: Python :: 3.8
Classifier: Programming Language :: Python :: 3.9
Classifier: Programming Language :: Python :: 3.10
Classifier: Programming Language :: Python :: 3.11
Requires-Dist: attrs (>=20.1.0)
Requires-Dist: httpx (>=0.22.0)
Requires-Dist: python-dateutil (>=2.8.0)
Requires-Dist: typing-extensions (>=4.4.0,<5.0.0) ; python_version < "3.8"
Project-URL: Repository, https://github.com/expobrain/python-modulr-client
